kivyblocks/__init__.py
kivyblocks/aplayer.py
kivyblocks/async_app.py
kivyblocks/baseWidget.py
kivyblocks/blocks.py
kivyblocks/blocksapp.py
kivyblocks/databuf.py
kivyblocks/datalist.py
kivyblocks/derivedWidget.py
kivyblocks/externalwidgetmanager.py
kivyblocks/pagescontainer.py
kivyblocks/threadcall.py
kivyblocks/toolbar.py
kivyblocks/uploadfile.py
kivyblocks/utils.py
kivyblocks/vplayer.py
kivyblocks/datagrid/BorderBehavior.py
kivyblocks/datagrid/Datagrid.py
kivyblocks/datagrid/__init__.py
kivyblocks/imgs/bullet_arrow_down.png
kivyblocks/imgs/bullet_arrow_right.png
kivyblocks/imgs/folder.png
kivyblocks/imgs/picture_empty.png
kivyblocks/ttf/DroidSansFallback.ttf
kivyblocks/widgetExt/__init__.py
kivyblocks/widgetExt/androidwebview.py
kivyblocks/widgetExt/binstateimage.py
kivyblocks/widgetExt/camera.py
kivyblocks/widgetExt/camerabutton.py
kivyblocks/widgetExt/dataloader.py
kivyblocks/widgetExt/filedataloader.py
kivyblocks/widgetExt/httpdataloader.py
kivyblocks/widgetExt/inputext.py
kivyblocks/widgetExt/jsoncodeinput.py
kivyblocks/widgetExt/messager.py
kivyblocks/widgetExt/phonebutton.py
kivyblocks/widgetExt/scrollwidget.py
kivyblocks/widgetExt/sqldataloadder.py
kivyblocks/widgetExt/tree.py
kivyblocks-0.0.3.dist-info/METADATA
kivyblocks-0.0.3.dist-info/WHEEL
kivyblocks-0.0.3.dist-info/top_level.txt
kivyblocks-0.0.3.dist-info/RECORD
